setup.py
musdex/__init__.py
musdex/__main__.py
musdex/commands.py
musdex/config.py
musdex/formatters.py
musdex/handlers.py
musdex/vcs.py
musdex.egg-info/PKG-INFO
musdex.egg-info/SOURCES.txt
musdex.egg-info/dependency_links.txt
musdex.egg-info/entry_points.txt
musdex.egg-info/top_level.txt
musdex.egg-info/zip-safe