Metadata-Version: 1.1
Name: musdex
Version: 17.9.12
Summary: musdex -- VCS-aware zip archive tool
Home-page: http://musdex.code.worldmaker.net
Author: Max Battcher
Author-email: me@worldmaker.net
License: Microsoft Reciprocal License (Ms-RL)
Platform: UNKNOWN
Classifier: Development Status :: 4 - Beta
Classifier: Environment :: Console
Classifier: Intended Audience :: Developers
Classifier: Operating System :: OS Independent
Classifier: Programming Language :: Python
Classifier: Programming Language :: Python :: 3.5
Classifier: Topic :: Software Development :: Version Control
Requires: argparse
Requires: yaml
